gstop/__init__.py
gstop/common.py
gstop/stopper.py
gstop-0.2.4.dist-info/METADATA
gstop-0.2.4.dist-info/WHEEL
gstop-0.2.4.dist-info/top_level.txt
gstop-0.2.4.dist-info/RECORD
