Metadata-Version: 2.1
Name: gstop
Version: 0.2.4
Summary: Generation Stopping Criteria for transformers Language Model
Author-email: ksterx <kostonerx@gmail.com>
Classifier: Programming Language :: Python :: 3
Requires-Python: >=3.10
Requires-Dist: transformers
Requires-Dist: torch
Requires-Dist: loguru
Provides-Extra: dev
Requires-Dist: pytest; extra == "dev"
Requires-Dist: ruff; extra == "dev"
